{
  "content": {
    "English": {
      "description": "Lesson 46 vocabulary.",
      "title": "Minna no Nihongo N4 Lesson 46"
    },
    "Russian": {
      "description": "Слова урока 46.",
      "title": "Minna no Nihongo N4 Урок 46"
    }
  },
  "level": "N4",
  "words": [
    "ガス",
    "ベル",
    "レンジ",
    "今",
    "付く",
    "何",
    "便",
    "入学",
    "具合",
    "出る",
    "出来事",
    "半年",
    "卒業",
    "原因",
    "只",
    "向かう",
    "宅配",
    "居る",
    "届く",
    "床",
    "待つ",
    "慌てる",
    "成る",
    "所",
    "方",
    "有る",
    "来る",
    "此方",
    "渡す",
    "焼く",
    "焼ける",
    "申し訳",
    "留守",
    "番",
    "良い",
    "転ぶ",
    "返る",
    "順",
    "鳴る"
  ]
}