{
	"content": {
		"English": {
			"description": "Lesson 33 vocabulary.",
			"title": "Minna no Nihongo N4 Lesson 33"
		},
		"Russian": {
			"description": "Слова урока 33.",
			"title": "Minna no Nihongo N4 Урок 33"
		}
	},
	"level": "N4",
	"words": [
		"こう",
		"しゅっ",
		"ちゅう",
		"で",
		"どう",
		"もう",
		"もっと",
		"ボール",
		"マーク",
		"リサイクル",
		"仕様",
		"伝える",
		"元々",
		"入り口",
		"割り引く",
		"助け合う",
		"危険",
		"同じ",
		"周",
		"咳",
		"地震",
		"外す",
		"始まる",
		"守る",
		"幾ら",
		"後",
		"悲しい",
		"愚痴",
		"戻る",
		"投げる",
		"挨拶",
		"放題",
		"有る",
		"気持ち",
		"注意",
		"為る",
		"無量",
		"焼酎",
		"相手",
		"立ち入る",
		"締め切る",
		"罰金",
		"規則",
		"言う",
		"諦める",
		"警察",
		"起きる",
		"逃げる",
		"違反",
		"金糸",
		"非常",
		"駄目",
		"駐車",
		"騒ぐ"
	]
}
