{
  "level": "N1",
  "content": {
    "Russian": {
      "title": "Migii N1 Урок 37",
      "description": "Словарный запас из урока 37 уровня N1 от Migii."
    },
    "English": {
      "title": "Migii N1 Lesson 37",
      "description": "Vocabulary from lesson 37 of N1 level by Migii."
    }
  },
  "words": [
    "弁論",
    "保守",
    "馴れ馴れしい",
    "樹立",
    "膳",
    "元来",
    "ルーズ",
    "購読",
    "カット",
    "中っ腹",
    "根底",
    "阻む",
    "防火",
    "虚ろ",
    "沿い",
    "天津",
    "真珠",
    "定義",
    "無邪気",
    "人体",
    "襟",
    "几帳面",
    "異論",
    "野外",
    "犯す",
    "立体",
    "途切れる",
    "移民",
    "朝寝坊",
    "お手上げ",
    "ややこしい",
    "借り",
    "判決",
    "占領",
    "受け止める",
    "経緯",
    "密度",
    "採掘",
    "分散",
    "日の丸",
    "回送",
    "徴収",
    "見地",
    "休戦",
    "僧",
    "カムバック",
    "保養",
    "害する",
    "箇条書き",
    "雑貨"
  ]
}