{
	"level": "N1",
	"content": {
		"Russian": {
			"title": "Migii N1 Урок 53",
			"description": "Словарный запас из урока 53 уровня N1 от Migii."
		},
		"English": {
			"title": "Migii N1 Lesson 53",
			"description": "Vocabulary from lesson 53 of N1 level by Migii."
		}
	},
	"words": [
		"あやふや",
		"タイヤ",
		"デモンストレーション",
		"ルール",
		"一",
		"一息",
		"不評",
		"主観",
		"入浴",
		"全滅",
		"初",
		"剥ぐ",
		"厳密",
		"及び",
		"受け継ぐ",
		"同調",
		"国交",
		"守衛",
		"安っぽい",
		"家出",
		"対応",
		"封",
		"工作",
		"巧妙",
		"押し込む",
		"振動",
		"断然",
		"未知",
		"栽培",
		"植わる",
		"業務",
		"模倣",
		"決断",
		"現地",
		"生きる",
		"税務",
		"等級",
		"簡易",
		"絶版",
		"肺",
		"自転",
		"舗装",
		"規定",
		"解除",
		"訂正",
		"訪れる",
		"進路",
		"領土"
	]
}
