{
	"level": "N3",
	"content": {
		"Russian": {
			"title": "Duolingo (EN) - Section 6 Unit 41",
			"description": "Слова из модуля: express feelings"
		},
		"English": {
			"title": "Duolingo (EN) - Section 6 Unit 41",
			"description": "Words from section/unit: express feelings"
		}
	},
	"words": [
		"やる気",
		"意欲",
		"対処",
		"励ます",
		"自慢",
		"ほっと",
		"娯楽",
		"歓迎",
		"困難",
		"癖",
		"失望",
		"支える",
		"同情",
		"印象",
		"味方",
		"友情",
		"頑固",
		"ひとりぼっち",
		"怖がる",
		"告白",
		"敬意",
		"親友",
		"人物",
		"愉快",
		"意地悪",
		"保証"
	]
}
