{
	"content": {
		"English": {
			"description": "Vocabulary from lesson 12 of N2 level by Migii.",
			"title": "Migii N2 Lesson 12"
		},
		"Russian": {
			"description": "Словарный запас из урока 12 уровня N2 от Migii.",
			"title": "Migii N2 Урок 12"
		}
	},
	"level": "N2",
	"words": [
		"どうせ",
		"ステージ",
		"ダイヤグラム",
		"ダム",
		"下書き",
		"不潔",
		"判事",
		"割り引き",
		"割合",
		"可決",
		"大学",
		"大工",
		"定価",
		"対立",
		"形式",
		"待ち合い",
		"心当たり",
		"損得",
		"整数",
		"書き取り",
		"材木",
		"構造",
		"欧米",
		"殻",
		"毎度",
		"汲む",
		"沙汰",
		"洗剤",
		"消防",
		"清掃",
		"為替",
		"率直",
		"生える",
		"生存",
		"盛る",
		"目覚まし",
		"直流",
		"直線",
		"真っ黒",
		"破れる",
		"缶詰め",
		"血圧",
		"複数",
		"言い付ける",
		"足る",
		"踏切",
		"転がす",
		"酸っぱい",
		"鈴",
		"集合"
	]
}
