{
	"level": "N5",
	"content": {
		"Russian": {
			"title": "Duolingo (RU) - Модуль 2 Раздел 16",
			"description": "Слова из модуля: Исследуйте новые места"
		},
		"English": {
			"title": "Duolingo (RU) - Модуль 2 Раздел 16",
			"description": "Words from module: Исследуйте новые места"
		}
	},
	"words": [
		"だいすき",
		"すてき",
		"おみやげ",
		"ポストカード",
		"おかし",
		"じんじゃ",
		"はな",
		"ふじさん",
		"山",
		"高い",
		"ピザや",
		"ラーメンや",
		"ゆうめい",
		"はらじゅく",
		"デザート",
		"あれ",
		"おてら",
		"何ですか",
		"たてもの",
		"きれい",
		"な",
		"ほんとうに",
		"ところ"
	]
}