{
  "level": "N3",
  "content": {
    "Russian": {
      "title": "Migii N3 Урок 23",
      "description": "Словарный запас из урока 23 уровня N3 от Migii."
    },
    "English": {
      "title": "Migii N3 Lesson 23",
      "description": "Vocabulary from lesson 23 of N3 level by Migii."
    }
  },
  "words": [
    "人種",
    "回復",
    "支店",
    "指す",
    "分",
    "知識",
    "余分",
    "きちんと",
    "教授",
    "日本",
    "礼",
    "狂う",
    "堀",
    "田",
    "事務",
    "生まれ",
    "恐ろしい",
    "汗",
    "金融",
    "覆う",
    "会",
    "悩む",
    "機関",
    "状況",
    "衝突",
    "努力",
    "局",
    "砂漠",
    "ライター",
    "商売",
    "稲",
    "端",
    "学期",
    "金庫",
    "劣る",
    "エンジン",
    "衣服",
    "進歩",
    "批判",
    "直接",
    "支払い",
    "似合う",
    "グラス",
    "便",
    "騒音",
    "大統領",
    "違いない",
    "地域",
    "周囲",
    "位置"
  ]
}