{
	"level": "N5",
	"content": {
		"Russian": {
			"title": "Migii N5 Урок 18",
			"description": "Словарный запас из урока 18 уровня N5 от Migii."
		},
		"English": {
			"title": "Migii N5 Lesson 18",
			"description": "Vocabulary from lesson 18 of N5 level by Migii."
		}
	},
	"words": [
		"地下鉄",
		"船",
		"飛行機",
		"空港",
		"乗る",
		"降りる",
		"歩く",
		"走る",
		"行く",
		"来る",
		"帰る",
		"郵便局",
		"病院",
		"銀行",
		"公園",
		"動物園",
		"遊園地",
		"映画館",
		"美術館",
		"博物館",
		"図書館",
		"学校",
		"教室",
		"食堂",
		"会社",
		"事務所",
		"工場",
		"受付",
		"お店",
		"売り場"
	]
}
