{
	"level": "N4",
	"content": {
		"Russian": {
			"title": "Duolingo (EN) - Section 4 Unit 21",
			"description": "Слова из модуля: talk about hobbies"
		},
		"English": {
			"title": "Duolingo (EN) - Section 4 Unit 21",
			"description": "Words from section/unit: talk about hobbies"
		}
	},
	"words": [
		"走",
		"撮り",
		"撮",
		"走り",
		"写真",
		"枚",
		"聞き",
		"泳ぎ",
		"聞",
		"音楽",
		"泳",
		"描き",
		"描",
		"遊",
		"あまり",
		"遊び",
		"散歩",
		"絵",
		"習い",
		"読",
		"習",
		"読み",
		"歌",
		"歌い",
		"手紙",
		"書き",
		"見",
		"書",
		"映画"
	]
}