{
	"level": "N4",
	"content": {
		"Russian": {
			"title": "Duolingo (EN) - Section 4 Unit 60",
			"description": "Слова из модуля: describe common objects"
		},
		"English": {
			"title": "Duolingo (EN) - Section 4 Unit 60",
			"description": "Words from section/unit: describe common objects"
		}
	},
	"words": [
		"最高",
		"最新",
		"最後",
		"最悪",
		"最近",
		"うまみ",
		"最も",
		"感",
		"痛み",
		"悲しみ",
		"甘み",
		"悲",
		"ひどい",
		"感じる",
		"美",
		"厳",
		"らしい",
		"厳しい",
		"っぽい",
		"美しい",
		"中々",
		"普",
		"変",
		"そう",
		"難しそう",
		"普通",
		"易しそう",
		"忙しそう",
		"みたい",
		"壊",
		"素",
		"ほど",
		"格",
		"素晴らしい",
		"格好",
		"壊れる",
		"ように",
		"ような",
		"形",
		"よう",
		"様子",
		"おかしい"
	]
}
